odoo/addons/product_template_multi_link/README.rst
odoo/addons/product_template_multi_link/__init__.py
odoo/addons/product_template_multi_link/__manifest__.py
odoo/addons/product_template_multi_link/data/product_template_link_type.xml
odoo/addons/product_template_multi_link/demo/product_template_link.xml
odoo/addons/product_template_multi_link/demo/product_template_link_type.xml
odoo/addons/product_template_multi_link/i18n/am.po
odoo/addons/product_template_multi_link/i18n/ar.po
odoo/addons/product_template_multi_link/i18n/bg.po
odoo/addons/product_template_multi_link/i18n/bs.po
odoo/addons/product_template_multi_link/i18n/ca.po
odoo/addons/product_template_multi_link/i18n/cs.po
odoo/addons/product_template_multi_link/i18n/da.po
odoo/addons/product_template_multi_link/i18n/de.po
odoo/addons/product_template_multi_link/i18n/el_GR.po
odoo/addons/product_template_multi_link/i18n/en_GB.po
odoo/addons/product_template_multi_link/i18n/es.po
odoo/addons/product_template_multi_link/i18n/es_AR.po
odoo/addons/product_template_multi_link/i18n/es_CL.po
odoo/addons/product_template_multi_link/i18n/es_CO.po
odoo/addons/product_template_multi_link/i18n/es_CR.po
odoo/addons/product_template_multi_link/i18n/es_DO.po
odoo/addons/product_template_multi_link/i18n/es_EC.po
odoo/addons/product_template_multi_link/i18n/es_ES.po
odoo/addons/product_template_multi_link/i18n/es_MX.po
odoo/addons/product_template_multi_link/i18n/es_PE.po
odoo/addons/product_template_multi_link/i18n/es_PY.po
odoo/addons/product_template_multi_link/i18n/es_VE.po
odoo/addons/product_template_multi_link/i18n/et.po
odoo/addons/product_template_multi_link/i18n/eu.po
odoo/addons/product_template_multi_link/i18n/fa.po
odoo/addons/product_template_multi_link/i18n/fi.po
odoo/addons/product_template_multi_link/i18n/fr.po
odoo/addons/product_template_multi_link/i18n/fr_CA.po
odoo/addons/product_template_multi_link/i18n/fr_CH.po
odoo/addons/product_template_multi_link/i18n/gl.po
odoo_addon_product_template_multi_link-18.0.1.0.1.1.dist-info/METADATA
odoo_addon_product_template_multi_link-18.0.1.0.1.1.dist-info/WHEEL
odoo_addon_product_template_multi_link-18.0.1.0.1.1.dist-info/top_level.txt
odoo_addon_product_template_multi_link-18.0.1.0.1.1.dist-info/RECORD
